gwenlake/__init__.py
gwenlake/base/__init__.py
gwenlake/base/exceptions.py
gwenlake/base/types.py
gwenlake/client/__init__.py
gwenlake/client/chat.py
gwenlake/client/constants.py
gwenlake/client/datasets.py
gwenlake/client/embeddings.py
gwenlake/client/files.py
gwenlake/client/generation.py
gwenlake/client/main.py
gwenlake/client/models.py
gwenlake/client/prompts.py
gwenlake/client/reader.py
gwenlake/client/resource.py
gwenlake/wrappers/__init__.py
gwenlake/wrappers/langchain/__init__.py
gwenlake/wrappers/langchain/embeddings.py
gwenlake/wrappers/langchain/selfquery.py
gwenlake-0.4.1.dist-info/LICENSE
gwenlake-0.4.1.dist-info/METADATA
gwenlake-0.4.1.dist-info/WHEEL
gwenlake-0.4.1.dist-info/top_level.txt
gwenlake-0.4.1.dist-info/RECORD
