Metadata-Version: 2.2
Name: gwenlake
Version: 0.4.1
Summary: Gwenlake framework
Home-page: https://github.com/gwenlake/gwenlake-python
Author: The Gwenlake Team
Author-email: info@gwenlake.com
Requires-Python: >=3.11
License-File: LICENSE
Dynamic: author
Dynamic: author-email
Dynamic: home-page
Dynamic: requires-python
